[
  {
    "id": "i1",
    "name": "Spun Filter",
    "sku": "SF-001",
    "price": 150,
    "stock": 120,
    "minStockAlert": 50
  },
  {
    "id": "i2",
    "name": "Carbon Filter",
    "sku": "CF-002",
    "price": 250,
    "stock": 45,
    "minStockAlert": 50
  },
  {
    "id": "i3",
    "name": "RO Membrane 75 GPD",
    "sku": "RM-075",
    "price": 1200,
    "stock": 12,
    "minStockAlert": 15
  },
  {
    "id": "i4",
    "name": "Booster Pump",
    "sku": "BP-100",
    "price": 2200,
    "stock": 8,
    "minStockAlert": 10
  }
]
